{"bounds": [-187.65, 17.62, -64.51, 71.44], "dams": 537686, "ranked_dams": 481587, "recon_dams": 31898, "ranked_largefish_barriers_dams": 476528, "ranked_smallfish_barriers_dams": 481587, "removed_dams": 2226, "removed_dams_gain_miles": 98283.4, "removed_dams_by_year": "942/53|23581.60,157/11|18704.24,335/17|21301.21,596/29|26102.33,57/4|853.70,45/2|3612.91,50/3|2022.55,44/5|2104.83", "total_small_barriers": 218956, "small_barriers": 110940, "ranked_small_barriers": 71182, "ranked_largefish_barriers_small_barriers": 53878, "ranked_smallfish_barriers_small_barriers": 84790, "removed_small_barriers": 6485, "removed_small_barriers_gain_miles": 33821.8, "removed_small_barriers_by_year": "481/78|2250.64,279/39|665.00,2053/452|6660.73,2780/635|13882.17,311/61|1858.98,194/28|4780.56,190/35|1877.90,197/40|1845.79", "crossings": 5838110}