{"bounds": [-187.65, 17.62, -64.51, 71.44], "dams": 558203, "ranked_dams": 500844, "recon_dams": 37783, "ranked_largefish_barriers_dams": 491616, "ranked_smallfish_barriers_dams": 500844, "removed_dams": 3182, "removed_dams_gain_miles": 207441.4, "removed_dams_by_year": "585/73|45212.49,306/22|26882.45,609/38|43002.27,1081/71|49749.23,108/9|8699.18,90/5|4800.80,104/10|4164.34,169/8|10110.87,114/7|9432.78,16/2|5386.95", "total_small_barriers": 343997, "small_barriers": 163010, "ranked_small_barriers": 91013, "ranked_largefish_barriers_small_barriers": 71461, "ranked_smallfish_barriers_small_barriers": 125310, "removed_small_barriers": 9373, "removed_small_barriers_gain_miles": 52753.2, "removed_small_barriers_by_year": "1912/349|8845.35,310/43|900.20,2795/603|10587.76,3105/708|19274.45,288/55|2812.85,199/31|4909.35,257/54|1910.18,291/50|2029.20,184/40|1196.23,32/4|287.61", "total_road_crossings": 6305747, "unsurveyed_road_crossings": 5961620}