{"southeast": {"dams": 147126, "on_network_dams": 122066, "miles": 8.443, "total_barriers": 27537, "barriers": 11727, "on_network_barriers": 10949, "crossings": 1193040}, "State": [{"id": "Florida", "dams": 5490, "total_barriers": 1505}, {"id": "North Carolina", "dams": 6067, "total_barriers": 1774}, {"id": "Louisiana", "dams": 918, "total_barriers": 717}, {"id": "Georgia", "dams": 31124, "total_barriers": 637}, {"id": "Alabama", "dams": 17272, "total_barriers": 2629}, {"id": "Texas", "dams": 18544, "total_barriers": 569}, {"id": "South Carolina", "dams": 3326, "total_barriers": 954}, {"id": "Oklahoma", "dams": 13287, "total_barriers": 712}, {"id": "Tennessee", "dams": 4426, "total_barriers": 484}, {"id": "Kentucky", "dams": 3235, "total_barriers": 916}, {"id": "Arkansas", "dams": 5989, "total_barriers": 2972}, {"id": "Mississippi", "dams": 7056, "total_barriers": 931}, {"id": "Missouri", "dams": 12920, "total_barriers": 9770}, {"id": "Puerto Rico", "dams": 392, "total_barriers": 28}, {"id": "Virginia", "dams": 8046, "total_barriers": 2880}]}